doorbell/__init__.py
doorbell/_six.py
doorbell/_version.py
doorbell-0.2.dist-info/LICENSE.txt
doorbell-0.2.dist-info/METADATA
doorbell-0.2.dist-info/WHEEL
doorbell-0.2.dist-info/top_level.txt
doorbell-0.2.dist-info/RECORD
