Metadata-Version: 2.1
Name: doorbell
Version: 0.2
Summary: A visitor pattern implementation for Python
Home-page: https://github.com/tbhartman/doorbell
Author: Tim Hartman
Author-email: tbhartman@gmail.com
License: MIT
Keywords: visitor
Platform: UNKNOWN
Classifier: Development Status :: 1 - Planning
Classifier: Intended Audience :: Developers
Classifier: Topic :: Utilities
Classifier: License :: OSI Approved :: MIT License
Classifier: Programming Language :: Python
Classifier: Programming Language :: Python :: 2
Classifier: Programming Language :: Python :: 2.7
Classifier: Programming Language :: Python :: 3
Classifier: Programming Language :: Python :: 3.4
Classifier: Programming Language :: Python :: 3.5
Classifier: Programming Language :: Python :: 3.6
Classifier: Programming Language :: Python :: 3.7
Provides-Extra: test
Requires-Dist: coverage; extra == 'test'
Requires-Dist: flake8; extra == 'test'
Requires-Dist: pytest; extra == 'test'
Requires-Dist: pytest-cov; extra == 'test'
Requires-Dist: sphinx-rtd-theme; extra == 'test'
Requires-Dist: tox; extra == 'test'
Requires-Dist: versioneer; extra == 'test'
